<?xml version="1.0" encoding="utf-8" ?>
<dwsync>
<file name="cabezote_liquido.png" server="C:/AppServ/www/admin-7.7/" local="128879159148160000" remote="128879159140000000" />
<file name="cabezote.png" server="C:/AppServ/www/admin-7.7/" local="128879157104870000" remote="128879157100000000" />
<file name="cabezote_liquido.png" server="C:/AppServ/www/admin_muestra/" local="128884693461740000" remote="128884693460000000" />
<file name="cabezote.png" server="C:/AppServ/www/admin_muestra/" local="128884692928930000" remote="128884692920000000" />
<file name="logo_empresa.jpg" server="C:/AppServ/www/admin_muestra/" local="128879105444330000" remote="128879105440000000" />
<file name="logo_imaginamos.jpg" server="C:/AppServ/www/admin_muestra/" local="128879104020840000" remote="128879104020000000" />
<file name="cabezote_liquido.png" server="C:/AppServ/www/cwv_desarrollo" local="129645468412998742" remote="129645468410000000" />
<file name="cabezote.png" server="C:/AppServ/www/cwv_desarrollo" local="129645468417108977" remote="129645468410000000" />
<file name="logo_imaginamos.jpg" server="C:/AppServ/www/cwv_desarrollo" local="129645468405438309" remote="129645468400000000" />
</dwsync>